pydantic_to_pyarrow/__init__.py
pydantic_to_pyarrow/py.typed
pydantic_to_pyarrow/schema.py
pydantic_to_pyarrow-0.1.6.dist-info/METADATA
pydantic_to_pyarrow-0.1.6.dist-info/WHEEL
pydantic_to_pyarrow-0.1.6.dist-info/licenses/LICENSE
pydantic_to_pyarrow-0.1.6.dist-info/RECORD
