Metadata-Version: 2.4
Name: pydantic-to-pyarrow
Version: 0.1.6
Summary: Conversion from pydantic models to pyarrow schemas
Project-URL: Homepage, https://github.com/simw/pydantic-to-pyarrow
Project-URL: Repository, https://github.com/simw/pydantic-to-pyarrow
Project-URL: Issues, https://github.com/simw/pydantic-to-pyarrow/issues
Author-email: Simon Wicks <simw@users.noreply.github.com>
License-File: LICENSE
Classifier: Development Status :: 3 - Alpha
Classifier: Environment :: Console
Classifier: Environment :: MacOS X
Classifier: Intended Audience :: Developers
Classifier: Intended Audience :: Information Technology
Classifier: License :: OSI Approved :: MIT License
Classifier: Operating System :: OS Independent
Classifier: Programming Language :: Python
Classifier: Programming Language :: Python :: 3
Classifier: Programming Language :: Python :: 3 :: Only
Classifier: Programming Language :: Python :: 3.8
Classifier: Programming Language :: Python :: 3.9
Classifier: Programming Language :: Python :: 3.10
Classifier: Programming Language :: Python :: 3.11
Classifier: Programming Language :: Python :: 3.12
Classifier: Programming Language :: Python :: 3.13
Classifier: Topic :: Software Development :: Libraries :: Python Modules
Classifier: Typing :: Typed
Requires-Python: >=3.8
Requires-Dist: numpy<1.25; python_version < '3.9'
Requires-Dist: numpy>1.25; python_version >= '3.12'
Requires-Dist: pyarrow>=11.0
Requires-Dist: pyarrow>=18.0; python_version >= '3.13'
Requires-Dist: pydantic>=2.0
Requires-Dist: pydantic>=2.8; python_version >= '3.13'
Requires-Dist: typing-extensions>=4.6.1
